ixten
