Metadata-Version: 1.0
Name: ixten
Version: 0.1.3
Summary: A tool to verify whether some ports are opened or not
Home-page: UNKNOWN
Author: Félix Brezo (@febrezo)
Author-email: UNKNOWN
License: GNU GPLv3+
Platform: UNKNOWN
